[1,["1c9521490","1b78a9669"],["_textureSetter"],["cc.SpriteFrame"],0,[[[{"name":"pao_4","rect":[3,799,130,126],"offset":[0,0],"originalSize":[130,126],"capInsets":[0,0,0,0]}],[0],0,[0],[0],[0]],[[{"name":"pao_2","rect":[3,3,135,146],"offset":[0,0],"originalSize":[135,146],"rotated":1,"capInsets":[0,0,0,0]}],[0],0,[0],[0],[1]],[[{"name":"pao_1","rect":[803,477,180,180],"offset":[0,0],"originalSize":[180,180],"capInsets":[0,0,0,0]}],[0],0,[0],[0],[0]],[[{"name":"pao_3","rect":[3,144,145,145],"offset":[0,0],"originalSize":[145,145],"capInsets":[0,0,0,0]}],[0],0,[0],[0],[1]]]]